kite_connect_lite/__init__.py
kite_connect_lite/main.py
kite_connect_lite/models/generate_session_model.py
kite_connect_lite/models/login_url_model.py
kite_connect_lite/models/place_normal_order_model.py
kite_connect_lite-0.0.3.dist-info/METADATA
kite_connect_lite-0.0.3.dist-info/WHEEL
kite_connect_lite-0.0.3.dist-info/RECORD
