Metadata-Version: 2.1
Name: kite_connect_lite
Version: 0.0.3
Summary: A user-friendly wrapper for the Kite Connect library
Author: AST-LW
Author-email: walkthroughfrom2020@gmail.com
Requires-Python: >=3.9,<4.0
Classifier: Programming Language :: Python :: 3
Classifier: Programming Language :: Python :: 3.9
Classifier: Programming Language :: Python :: 3.10
Classifier: Programming Language :: Python :: 3.11
Classifier: Programming Language :: Python :: 3.12
Requires-Dist: kiteconnect (>=5.0.1,<6.0.0)
Requires-Dist: pandas (>=2.2.1,<3.0.0)
Requires-Dist: pydantic (>=2.6.4,<3.0.0)
Requires-Dist: python-dotenv (>=1.0.1,<2.0.0)
